[
  {
    "title": "\u30d6\u30c3\u30c1\u30e3\u30fc\u304c\u30db\u30ef\u30a4\u30c8\u30cf\u30a6\u30b9\u306e\u58c1\u3076\u3061\u7834\u3063\u3066\u304d\u305f\u6642\u306e\u30db\u30fc\u30e0\u30e9\u30f3\u30c0\u30fc\u306e\u67d4\u3089\u304b\u306a\u8868\u60c5\u3063\u3066 \u3042\u306e\u653e\u9001\u306e\u6f14\u8aac\u3092\u7d42\u3048\u3066\u3057\u307e\u3063\u3066\u8ab0\u304b\u306b\u611b\u3055\u308c\u308b\u3053\u3068\u306f\u3082\u3046\u306a\u304f\u306a\u308a\u6050\u6016\u306e\u5bfe\u8c61\u306b\u3057\u304b\u306a\u3089\u306a\u3044\u904b\u547d\u3092\u7d42\u308f\u3089\u305b\u3066\u304f\u308c\u308b\u4eba\u304c\u6765\u305f\u304b\u3089\u306a\u306e\u304b",
    "source": "@kaborobot",
    "description": "",
    "url": "https://nitter.net/kaborobot/status/2058205543760838842#m",
    "date": "2026-06-02",
    "category": "Twitter"
  },
  {
    "title": "MAI-Code-1-Flash",
    "source": "Hacker News",
    "description": "HN Score: 355 | 161 comments",
    "url": "https://microsoft.ai/news/introducingmai-code-1-flash/",
    "score": 355,
    "date": "2026-06-02",
    "category": "AI News"
  },
  {
    "title": "\u4eca\u56de\u306e\u602a\u7570\u3063\u3066 \u300c\u3082\u3057\u5cb8\u8fba\u9732\u4f34\u304c\u307f\u3093\u306a\u306b\u30c1\u30e4\u30db\u30e4\u3055\u308c\u308b\u305f\u3081\u306b\u6f2b\u753b\u3092\u63cf\u3044\u3066\u305f\u3089\u300d \u3060\u3063\u305f\u306a #\u6cc9\u4eac\u9999\u306f\u9ed9\u3089\u306a\u3044",
    "source": "@kaborobot",
    "description": "",
    "url": "https://nitter.net/kaborobot/status/2051300761896972364#m",
    "date": "2026-06-02",
    "category": "Twitter"
  },
  {
    "title": "California\u2019s university system went all in on AI, now it's tearing itself apart",
    "source": "Hacker News",
    "description": "HN Score: 48 | 28 comments",
    "url": "https://www.nytimes.com/2026/06/01/magazine/ai-university-college-california.html",
    "score": 48,
    "date": "2026-06-02",
    "category": "AI News"
  },
  {
    "title": "RT by @EMostaque: II-Agent is now live on the App Store. Your sovereign AI workspace for building, researching, writing, designing, and automating fro",
    "source": "@EMostaque",
    "description": "",
    "url": "https://nitter.net/ii_posts/status/2061825361126543439#m",
    "date": "2026-06-02",
    "category": "Twitter"
  },
  {
    "title": "Gmail thinks I'm stupid, so I left",
    "source": "Hacker News",
    "description": "HN Score: 536 | 327 comments",
    "url": "https://moddedbear.com/gmail-thinks-im-stupid-so-i-left",
    "score": 536,
    "date": "2026-06-02",
    "category": "AI News"
  },
  {
    "title": "RT by @DrJimFan: Mark: 1/ First milestone: the Physical Turing Test. You literally can\u2019t tell if a human or robot is doing the task. 2/ Next: Physical",
    "source": "@DrJimFan",
    "description": "",
    "url": "https://nitter.net/CyberRobooo/status/2053149920740450732#m",
    "date": "2026-06-02",
    "category": "Twitter"
  },
  {
    "title": "Open Repair Data Standard \u2013 Open Repair Alliance",
    "source": "Hacker News",
    "description": "HN Score: 82 | 2 comments",
    "url": "https://openrepair.org/open-data/open-standard/",
    "score": 82,
    "date": "2026-06-02",
    "category": "AI News"
  },
  {
    "title": "RT by @DrJimFan: Jim is always a crowd favorite at AI Ascent. His ability to simplify the latest research into a clear 'what and why it matters' while",
    "source": "@DrJimFan",
    "description": "",
    "url": "https://nitter.net/Alfred_Lin/status/2052847050379936113#m",
    "date": "2026-06-02",
    "category": "Twitter"
  },
  {
    "title": "Adafruit receives demand letter from Fenwick legal counsel on behalf of Flux.ai",
    "source": "Hacker News",
    "description": "HN Score: 598 | 246 comments",
    "url": "https://blog.adafruit.com/",
    "score": 598,
    "date": "2026-06-02",
    "category": "AI News"
  },
  {
    "title": "My friend deployed his first website with a couple of prompts. He doesn't understand what 'HTML', 'security', or 'VPC' mean. He doesn't care. His GPT-",
    "source": "@svpino",
    "description": "",
    "url": "https://nitter.net/svpino/status/2061925133275861481#m",
    "date": "2026-06-02",
    "category": "Twitter"
  },
  {
    "title": "Now AI agents need what RSS does",
    "source": "Hacker News",
    "description": "HN Score: 42 | 15 comments",
    "url": "https://julienreszka.com/blog/rss-is-back-ai-agents-are-reading-it/",
    "score": 42,
    "date": "2026-06-02",
    "category": "AI News"
  },
  {
    "title": "Here is an open-source tool to generate a complete dataset. 1. Describe the data you want 2. An orchestrator agent searches the web 3. Sub-agents run ",
    "source": "@svpino",
    "description": "",
    "url": "https://nitter.net/svpino/status/2061901892448555160#m",
    "date": "2026-06-02",
    "category": "Twitter"
  },
  {
    "title": "Npm-scan: Modern supply chain security for the npm ecosystem",
    "source": "Hacker News",
    "description": "HN Score: 6 | 0 comments",
    "url": "https://github.com/lateos-ai/npm-scan",
    "score": 6,
    "date": "2026-06-02",
    "category": "AI News"
  },
  {
    "title": "Finally, Microsoft enters the AI arena! They just announced two foundation models - MAI and Mai-Flash They used to have a great research lab... and ea",
    "source": "@bindureddy",
    "description": "",
    "url": "https://nitter.net/bindureddy/status/2061877732708176214#m",
    "date": "2026-06-02",
    "category": "Twitter"
  },
  {
    "title": "Trump signs downsized AI order after weeks of reversals",
    "source": "Hacker News",
    "description": "HN Score: 156 | 107 comments",
    "url": "https://www.politico.com/news/2026/06/02/trump-signs-downsized-ai-order-00946389",
    "score": 156,
    "date": "2026-06-02",
    "category": "AI News"
  },
  {
    "title": "\ud83d\udea8 Agent Swarm - Build Complex SaaS Apps And Automations On The Abacus AI Super Computer! Create multi-agent swarms using top models including Opus 4.8",
    "source": "@bindureddy",
    "description": "",
    "url": "https://nitter.net/bindureddy/status/2061654798919696549#m",
    "date": "2026-06-02",
    "category": "Twitter"
  },
  {
    "title": "Show HN: Paseo \u2013 Beautiful open-source coding agent interface",
    "source": "Hacker News",
    "description": "HN Score: 10 | 2 comments",
    "url": "https://github.com/getpaseo/paseo",
    "score": 10,
    "date": "2026-06-02",
    "category": "AI News"
  },
  {
    "title": "Great Question (YC W21) Is Hiring Applied AI Interns",
    "source": "Hacker News",
    "description": "HN Score: 1 | 0 comments",
    "url": "https://www.ycombinator.com/companies/great-question/jobs/J5TNvQH-ai-engineer-intern",
    "score": 1,
    "date": "2026-06-02",
    "category": "AI News"
  }
]